rtl/motor/pid_controller.v
// =============================================================================
// Module  : pid_controller
// Project : Tang Nano 9K – PID Motor Controller over Ethernet
// File    : rtl/pid_controller.v
//
// Purpose : Fixed-point discrete PID controller.
//
//   Output = Kp*e + Ki*∑e + Kd*(e - e_prev)       [per sample tick]
//
// Fixed-point format (8.8): gain_register / 256 = actual real gain
//   Example: kp = 16'h0100 (256) → Kp_real = 1.0
//            ki = 16'h0020 (32)  → Ki_real = 0.125
//            kd = 16'h0080 (128) → Kd_real = 0.5
//
// Anti-windup: integral accumulator is clamped to ±ICLAMP to prevent
//              saturation from very long step errors.
//
// Output saturation: signed 16-bit, i.e. ±32767.
//
// Parameters
//   ICLAMP  – Integral windup clamp (32-bit signed magnitude, default ±10M)
//
// Interface
//   clk         – System clock
//   rst         – Synchronous active-high reset
//   sample_tick – 1-cycle pulse that triggers one PID computation
//   enable      – PID active when HIGH; output holds when LOW
//   kp/ki/kd    – Gains (8.8 fixed-point, unsigned 16-bit)
//   setpoint    – Target value (signed 16-bit)
//   feedback    – Measured value (signed 16-bit, e.g. encoder position>>16)
//   pid_out     – PID output (signed 16-bit, drives motor_bridge)
//   error_out   – Current error for telemetry (signed 16-bit)
//   integral_dbg– Raw integral accumulator for debug/telemetry
// =============================================================================

`default_nettype none

module pid_controller #(
    parameter signed [31:0] ICLAMP = 32'sh00989680  // ±10 000 000 (prevents windup)
)(
    input  wire              clk,
    input  wire              rst,
    input  wire              sample_tick,
    input  wire              enable,

    input  wire [15:0]       kp,
    input  wire [15:0]       ki,
    input  wire [15:0]       kd,

    input  wire signed [15:0] setpoint,
    input  wire signed [15:0] feedback,

    output reg  signed [15:0] pid_out,
    output reg  signed [15:0] error_out,
    output wire signed [31:0] integral_dbg
);

    // -------------------------------------------------------------------------
    // Internal registers
    // -------------------------------------------------------------------------
    reg  signed [31:0] integrator;
    reg  signed [15:0] prev_error;

    assign integral_dbg = integrator;

    // -------------------------------------------------------------------------
    // Combinatorial terms (computed every cycle, registered on sample_tick)
    // -------------------------------------------------------------------------
    wire signed [15:0] error      = setpoint - feedback;
    wire signed [31:0] p_term     = ($signed({1'b0, kp}) * error) >>> 8;
    wire signed [31:0] d_term     = ($signed({1'b0, kd}) * (error - prev_error)) >>> 8;
    wire signed [31:0] i_contrib  = integrator >>> 8;

    // Raw sum before saturation (33-bit to catch overflow)
    wire signed [33:0] raw_sum    = $signed(p_term) + $signed(i_contrib) + $signed(d_term);

    // Next integrator value (for anti-windup logic)
    wire signed [31:0] i_next     = integrator + ($signed({1'b0, ki}) * error);

    // -------------------------------------------------------------------------
    // Sequential logic
    // -------------------------------------------------------------------------
    always @(posedge clk) begin
        if (rst) begin
            integrator <= 32'sd0;
            prev_error <= 16'sd0;
            pid_out    <= 16'sd0;
            error_out  <= 16'sd0;
        end else if (sample_tick && enable) begin

            // -- Error output (for telemetry) ---------------------------------
            error_out <= error;

            // -- Anti-windup integral clamp -----------------------------------
            if ($signed(i_next) > $signed(ICLAMP))
                integrator <= $signed(ICLAMP);
            else if ($signed(i_next) < $signed(-ICLAMP))
                integrator <= $signed(-ICLAMP);
            else
                integrator <= i_next;

            // -- Output saturation to ±32767 ----------------------------------
            if ($signed(raw_sum) > 34'sh0000000_7FFF)
                pid_out <= 16'sh7FFF;
            else if ($signed(raw_sum) < 34'shFFFFFF_8000)
                pid_out <= 16'sh8000;
            else
                pid_out <= raw_sum[15:0];

            // -- Store previous error for derivative --------------------------
            prev_error <= error;
        end
    end

endmodule

`default_nettype wire

tb/tb_pid_controller.v
// =============================================================================
// Testbench : tb_pid_controller
// Project   : Tang Nano 9K – PID Motor Controller over Ethernet
// File      : tb/tb_pid_controller.v
//
// Purpose   : Verifies the pid_controller module using a simulated step input.
//   - Applies setpoint=16384 (0x4000) with feedback starting at 0
//   - Verifies output rises toward setpoint over time
//   - Verifies integral accumulates
//   - Verifies derivative fires correctly
//   - VCD waveform saved to data/sim_pid.vcd for GTKWave analysis
//
// Run:
//   iverilog -g2012 -o data/sim_pid tb/tb_pid_controller.v rtl/motor/pid_controller.v
//   vvp data/sim_pid
//   gtkwave data/sim_pid.vcd
// =============================================================================

`timescale 1ns/1ps

module tb_pid_controller;

    // -------------------------------------------------------------------------
    // DUT signals
    // -------------------------------------------------------------------------
    reg          clk        = 0;
    reg          rst        = 1;
    reg          sample_tick= 0;
    reg          enable     = 1;
    reg  [15:0]  kp         = 16'h0100;   // 1.0
    reg  [15:0]  ki         = 16'h0020;   // 0.125
    reg  [15:0]  kd         = 16'h0080;   // 0.5
    reg  signed [15:0] setpoint  = 16'sd0;
    reg  signed [15:0] feedback  = 16'sd0;

    wire signed [15:0] pid_out;
    wire signed [15:0] error_out;
    wire signed [31:0] integral_dbg;

    // -------------------------------------------------------------------------
    // Instantiate DUT
    // -------------------------------------------------------------------------
    pid_controller u_dut (
        .clk          (clk),
        .rst          (rst),
        .sample_tick  (sample_tick),
        .enable       (enable),
        .kp           (kp),
        .ki           (ki),
        .kd           (kd),
        .setpoint     (setpoint),
        .feedback     (feedback),
        .pid_out      (pid_out),
        .error_out    (error_out),
        .integral_dbg (integral_dbg)
    );

    // -------------------------------------------------------------------------
    // 50 MHz clock (20 ns period)
    // -------------------------------------------------------------------------
    always #10 clk = ~clk;

    // -------------------------------------------------------------------------
    // Task: Apply one sample tick and check output
    // -------------------------------------------------------------------------
    task apply_tick;
        begin
            @(posedge clk); #1;
            sample_tick = 1;
            @(posedge clk); #1;
            sample_tick = 0;
        end
    endtask

    // -------------------------------------------------------------------------
    // Pass/fail tracking
    // -------------------------------------------------------------------------
    integer pass_cnt = 0;
    integer fail_cnt = 0;

    task assert_gt;
        input signed [15:0] val;
        input signed [15:0] threshold;
        input [255:0]       label;
        begin
            if ($signed(val) > $signed(threshold)) begin
                $display("  PASS  [%0s] pid_out=%0d > %0d", label, val, threshold);
                pass_cnt = pass_cnt + 1;
            end else begin
                $display("  FAIL  [%0s] pid_out=%0d  SHOULD BE > %0d", label, val, threshold);
                fail_cnt = fail_cnt + 1;
            end
        end
    endtask

    // -------------------------------------------------------------------------
    // Main test sequence
    // -------------------------------------------------------------------------
    initial begin
        $dumpfile("data/sim_pid.vcd");
        $dumpvars(0, tb_pid_controller);

        $display("==============================================");
        $display("  PID Controller Testbench");
        $display("  Kp=1.0  Ki=0.125  Kd=0.5");
        $display("==============================================");

        // Release reset after 5 cycles
        repeat (5) @(posedge clk);
        rst      = 0;
        setpoint = 16'sd16384;   // 0x4000 = 25% of max

        // -------- Test 1: Step response – output should rise -----------------
        $display("\n[TEST 1] Step response (setpoint=16384, feedback=0)");
        repeat (10) begin
            apply_tick;
            $display("  tick: error=%0d  pid_out=%0d  integral=%0d",
                     error_out, pid_out, integral_dbg);
        end
        assert_gt(pid_out, 0, "pid_out>0 after step");

        // -------- Test 2: Closed-loop simulation ---------------------------
        $display("\n[TEST 2] Simulated motor (integrator drives feedback)");
        feedback = 16'sd0;
        repeat (30) begin
            apply_tick;
            // Simulate sluggish motor: feedback += pid_out/256
            feedback = feedback + (pid_out >>> 8);
            $display("  tick: fb=%0d  error=%0d  pid_out=%0d",
                     feedback, error_out, pid_out);
        end
        // After 30 ticks, feedback should have converged toward setpoint
        if ($signed(feedback) > 16'sd8000)
            $display("  PASS  [convergence] feedback=%0d reached > 8000", feedback);
        else
            $display("  WARN  [convergence] feedback=%0d still low (gains may need tuning)", feedback);

        // -------- Test 3: Disable PID – output should freeze ---------------
        $display("\n[TEST 3] Disable PID (output should hold)");
        enable = 0;
        begin
            reg signed [15:0] frozen_out;
            frozen_out = pid_out;
            apply_tick;
            apply_tick;
            if (pid_out == frozen_out) begin
                $display("  PASS  [disable] output held at %0d", pid_out);
                pass_cnt = pass_cnt + 1;
            end else begin
                $display("  FAIL  [disable] output changed to %0d (was %0d)", pid_out, frozen_out);
                fail_cnt = fail_cnt + 1;
            end
        end

        // -------- Test 4: Reset clears integrator --------------------------
        $display("\n[TEST 4] Reset clears state");
        rst = 1;
        @(posedge clk); #1;
        rst = 0;
        @(posedge clk); #1;
        if (integral_dbg == 0 && pid_out == 0) begin
            $display("  PASS  [reset] integral_dbg=%0d pid_out=%0d", integral_dbg, pid_out);
            pass_cnt = pass_cnt + 1;
        end else begin
            $display("  FAIL  [reset] integral_dbg=%0d pid_out=%0d (expected 0)", integral_dbg, pid_out);
            fail_cnt = fail_cnt + 1;
        end

        // -------- Summary --------------------------------------------------
        $display("\n==============================================");
        $display("  Total PASS: %0d  FAIL: %0d", pass_cnt, fail_cnt);
        $display("  VCD saved to: data/sim_pid.vcd");
        $display("==============================================");

        $finish;
    end

    // Timeout watchdog
    initial begin
        #10_000_000;
        $display("TIMEOUT – simulation exceeded 10 ms");
        $finish;
    end

endmodule

data/sim_pid.vcd
$date
	Sun Mar  1 23:39:25 2026
$end
$version
	Icarus Verilog
$end
$timescale
	1ps
$end
$scope module tb_pid_controller $end
$var wire 16 ! pid_out [15:0] $end
$var wire 32 " integral_dbg [31:0] $end
$var wire 16 # error_out [15:0] $end
$var reg 1 $ clk $end
$var reg 1 % enable $end
$var reg 16 & feedback [15:0] $end
$var reg 16 ' kd [15:0] $end
$var reg 16 ( ki [15:0] $end
$var reg 16 ) kp [15:0] $end
$var reg 1 * rst $end
$var reg 1 + sample_tick $end
$var reg 16 , setpoint [15:0] $end
$var integer 32 - fail_cnt [31:0] $end
$var integer 32 . pass_cnt [31:0] $end
$scope module u_dut $end
$var wire 1 $ clk $end
$var wire 1 % enable $end
$var wire 16 / feedback [15:0] $end
$var wire 32 0 integral_dbg [31:0] $end
$var wire 16 1 kd [15:0] $end
$var wire 16 2 ki [15:0] $end
$var wire 16 3 kp [15:0] $end
$var wire 1 * rst $end
$var wire 1 + sample_tick $end
$var wire 16 4 setpoint [15:0] $end
$var wire 34 5 raw_sum [33:0] $end
$var wire 32 6 p_term [31:0] $end
$var wire 32 7 i_next [31:0] $end
$var wire 32 8 i_contrib [31:0] $end
$var wire 16 9 error [15:0] $end
$var wire 32 : d_term [31:0] $end
$var parameter 32 ; ICLAMP $end
$var reg 16 < error_out [15:0] $end
$var reg 32 = integrator [31:0] $end
$var reg 16 > pid_out [15:0] $end
$var reg 16 ? prev_error [15:0] $end
$upscope $end
$scope begin $unm_blk_8 $end
$var reg 16 @ frozen_out [15:0] $end
$upscope $end
$scope task apply_tick $end
$upscope $end
$scope task assert_gt $end
$var reg 256 A label [255:0] $end
$var reg 16 B threshold [15:0] $end
$var reg 16 C val [15:0] $end
$upscope $end
$upscope $end
$enddefinitions $end
$comment Show the parameter values. $end
$dumpall
b100110001001011010000000 ;
$end
#0
$dumpvars
bx C
bx B
bx A
bx @
bx ?
bx >
bx =
bx <
bx :
b0 9
bx 8
bx 7
b0 6
bx 5
b0 4
b100000000 3
b100000 2
b10000000 1
bx 0
b0 /
b0 .
b0 -
b0 ,
0+
1*
b100000000 )
b100000 (
b10000000 '
b0 &
1%
0$
bx #
bx "
bx !
$end
#10000
b0 5
b0 :
b0 8
b0 #
b0 <
b0 !
b0 >
b0 ?
b0 7
b0 "
b0 0
b0 =
1$
#20000
0$
#30000
1$
#40000
0$
#50000
1$
#60000
0$
#70000
1$
#80000
0$
#90000
b100000000000000 6
b110000000000000 5
b10000000000000 :
b10000000000000000000 7
b100000000000000 9
b100000000000000 ,
b100000000000000 4
0*
1$
#100000
0$
#110000
1$
#111000
1+
#120000
0$
#130000
b0 :
b100100000000000 5
b100000000000 8
b100000000000000 ?
b110000000000000 !
b110000000000000 >
b100000000000000000000 7
b10000000000000000000 "
b10000000000000000000 0
b10000000000000000000 =
b100000000000000 #
b100000000000000 <
1$
#131000
0+
#140000
0$
#150000
1$
#151000
1+
#160000
0$
#170000
b101000000000000 5
b1000000000000 8
b100100000000000 !
b100100000000000 >
b110000000000000000000 7
b100000000000000000000 "
b100000000000000000000 0
b100000000000000000000 =
1$
#171000
0+
#180000
0$
#190000
1$
#191000
1+
#200000
0$
#210000
b101100000000000 5
b1100000000000 8
b101000000000000 !
b101000000000000 >
b1000000000000000000000 7
b110000000000000000000 "
b110000000000000000000 0
b110000000000000000000 =
1$
#211000
0+
#220000
0$
#230000
1$
#231000
1+
#240000
0$
#250000
b110000000000000 5
b10000000000000 8
b101100000000000 !
b101100000000000 >
b1010000000000000000000 7
b1000000000000000000000 "
b1000000000000000000000 0
b1000000000000000000000 =
1$
#251000
0+
#260000
0$
#270000
1$
#271000
1+
#280000
0$
#290000
b110100000000000 5
b10100000000000 8
b110000000000000 !
b110000000000000 >
b1100000000000000000000 7
b1010000000000000000000 "
b1010000000000000000000 0
b1010000000000000000000 =
1$
#291000
0+
#300000
0$
#310000
1$
#311000
1+
#320000
0$
#330000
b111000000000000 5
b11000000000000 8
b110100000000000 !
b110100000000000 >
b1110000000000000000000 7
b1100000000000000000000 "
b1100000000000000000000 0
b1100000000000000000000 =
1$
#331000
0+
#340000
0$
#350000
1$
#351000
1+
#360000
0$
#370000
b111100000000000 5
b11100000000000 8
b111000000000000 !
b111000000000000 >
b10000000000000000000000 7
b1110000000000000000000 "
b1110000000000000000000 0
b1110000000000000000000 =
1$
#371000
0+
#380000
0$
#390000
1$
#391000
1+
#400000
0$
#410000
b1000000000000000 5
b100000000000000 8
b111100000000000 !
b111100000000000 >
b10010000000000000000000 7
b10000000000000000000000 "
b10000000000000000000000 0
b10000000000000000000000 =
1$
#411000
0+
#420000
0$
#430000
1$
#431000
1+
#440000
0$
#450000
b1000100000000000 5
b100100000000000 8
b111111111111111 !
b111111111111111 >
b10100000000000000000000 7
b10010000000000000000000 "
b10010000000000000000000 0
b10010000000000000000000 =
1$
#451000
0+
#460000
0$
#470000
1$
#471000
1+
#480000
0$
#490000
b1001000000000000 5
b101000000000000 8
b10110000000000000000000 7
b10100000000000000000000 "
b10100000000000000000000 0
b10100000000000000000000 =
1$
#491000
b1 .
b111000001101001011001000101111101101111011101010111010000111110001100000010000001100001011001100111010001100101011100100010000001110011011101000110010101110000 A
b0 B
b111111111111111 C
0+
#500000
0$
#510000
1$
#511000
1+
#520000
0$
#530000
b1001100000000000 5
b101100000000000 8
b11000000000000000000000 7
b10110000000000000000000 "
b10110000000000000000000 0
b10110000000000000000000 =
1$
#531000
b11111110000001 6
b1001011101000001 5
b11111111111111111111111111000000 :
b10111111111000000100000 7
b11111110000001 9
b1111111 &
b1111111 /
0+
#540000
0$
#550000
1$
#551000
1+
#560000
0$
#570000
b0 :
b1001111101110001 5
b101111111110000 8
b11111110000001 ?
b11001111110000001000000 7
b10111111111000000100000 "
b10111111111000000100000 0
b10111111111000000100000 =
b11111110000001 #
b11111110000001 <
1$
#571000
b11111100000010 6
b1001111010110010 5
b11111111111111111111111111000000 :
b11001111101000001100000 7
b11111100000010 9
b11111110 &
b11111110 /
0+
#580000
0$
#590000
1$
#591000
1+
#600000
0$
#610000
b0 :
b1010011011010010 5
b110011111010000 8
b11111100000010 ?
b11011111011000010100000 7
b11001111101000001100000 "
b11001111101000001100000 0
b11001111101000001100000 =
b11111100000010 #
b11111100000010 <
1$
#611000
b11111010000011 6
b1010011000010011 5
b11111111111111111111111111000000 :
b11011111010000011000000 7
b11111010000011 9
b101111101 &
b101111101 /
0+
#620000
0$
#630000
1$
#631000
1+
#640000
0$
#650000
b0 :
b1010111000100011 5
b110111110100000 8
b11111010000011 ?
b11101110111000100100000 7
b11011111010000011000000 "
b11011111010000011000000 0
b11011111010000011000000 =
b11111010000011 #
b11111010000011 <
1$
#651000
b11111000000100 6
b1010110101100100 5
b11111111111111111111111111000000 :
b11101110110000101000000 7
b11111000000100 9
b111111100 &
b111111100 /
0+
#660000
0$
#670000
1$
#671000
1+
#680000
0$
#690000
b0 :
b1011010101100101 5
b111011101100001 8
b11111000000100 ?
b11111110010000111000000 7
b11101110110000101000000 "
b11101110110000101000000 0
b11101110110000101000000 =
b11111000000100 #
b11111000000100 <
1$
#691000
b11110110000101 6
b1011010010100110 5
b11111111111111111111111111000000 :
b11111110001000111100000 7
b11110110000101 9
b1001111011 &
b1001111011 /
0+
#700000
0$
#710000
1$
#711000
1+
#720000
0$
#730000
b0 :
b1011110010010110 5
b111111100010001 8
b11110110000101 ?
b100001101100001010000000 7
b11111110001000111100000 "
b11111110001000111100000 0
b11111110001000111100000 =
b11110110000101 #
b11110110000101 <
1$
#731000
b11110100000110 6
b1011101111010111 5
b11111111111111111111111111000000 :
b100001101011001010100000 7
b11110100000110 9
b1011111010 &
b1011111010 /
0+
#740000
0$
#750000
1$
#751000
1+
#760000
0$
#770000
b0 :
b1100001110111000 5
b1000011010110010 8
b11110100000110 ?
b100011100101001101100000 7
b100001101011001010100000 "
b100001101011001010100000 0
b100001101011001010100000 =
b11110100000110 #
b11110100000110 <
1$
#771000
b11110010000111 6
b1100001011111001 5
b11111111111111111111111111000000 :
b100011100100001110000000 7
b11110010000111 9
b1101111001 &
b1101111001 /
0+
#780000
0$
#790000
1$
#791000
1+
#800000
0$
#810000
b0 :
b1100101011001010 5
b1000111001000011 8
b11110010000111 ?
b100101011101010001100000 7
b100011100100001110000000 "
b100011100100001110000000 0
b100011100100001110000000 =
b11110010000111 #
b11110010000111 <
1$
#811000
b11110000001000 6
b1100101000001011 5
b11111111111111111111111111000000 :
b100101011100010010000000 7
b11110000001000 9
b1111111000 &
b1111111000 /
0+
#820000
0$
#830000
1$
#831000
1+
#840000
0$
#850000
b0 :
b1101000111001100 5
b1001010111000100 8
b11110000001000 ?
b100111010100010110000000 7
b100101011100010010000000 "
b100101011100010010000000 0
b100101011100010010000000 =
b11110000001000 #
b11110000001000 <
1$
#851000
b11101110001001 6
b1101000100001101 5
b11111111111111111111111111000000 :
b100111010011010110100000 7
b11101110001001 9
b10001110111 &
b10001110111 /
0+
#860000
0$
#870000
1$
#871000
1+
#880000
0$
#890000
b0 :
b1101010000011111 5
b1001100010010110 8
b11101110001001 ?
b101000000000011110100000 7
b100110001001011010000000 "
b100110001001011010000000 0
b100110001001011010000000 =
b11101110001001 #
b11101110001001 <
1$
#891000
b11101100001010 6
b1101001101100000 5
b11111111111111111111111111000000 :
b100111111111011111000000 7
b11101100001010 9
b10011110110 &
b10011110110 /
0+
#900000
0$
#910000
1$
#911000
1+
#920000
0$
#930000
b1101001110100000 5
b0 :
b11101100001010 ?
b11101100001010 #
b11101100001010 <
1$
#931000
b11101010001011 6
b1101001011100001 5
b11111111111111111111111111000000 :
b100111111110011111100000 7
b11101010001011 9
b10101110101 &
b10101110101 /
0+
#940000
0$
#950000
1$
#951000
1+
#960000
0$
#970000
b1101001100100001 5
b0 :
b11101010001011 ?
b11101010001011 #
b11101010001011 <
1$
#971000
b11101000001100 6
b1101001001100010 5
b11111111111111111111111111000000 :
b100111111101100000000000 7
b11101000001100 9
b10111110100 &
b10111110100 /
0+
#980000
0$
#990000
1$
#991000
1+
#1000000
0$
#1010000
b1101001010100010 5
b0 :
b11101000001100 ?
b11101000001100 #
b11101000001100 <
1$
#1011000
b11100110001101 6
b1101000111100011 5
b11111111111111111111111111000000 :
b100111111100100000100000 7
b11100110001101 9
b11001110011 &
b11001110011 /
0+
#1020000
0$
#1030000
1$
#1031000
1+
#1040000
0$
#1050000
b1101001000100011 5
b0 :
b11100110001101 ?
b11100110001101 #
b11100110001101 <
1$
#1051000
b11100100001110 6
b1101000101100100 5
b11111111111111111111111111000000 :
b100111111011100001000000 7
b11100100001110 9
b11011110010 &
b11011110010 /
0+
#1060000
0$
#1070000
1$
#1071000
1+
#1080000
0$
#1090000
b1101000110100100 5
b0 :
b11100100001110 ?
b11100100001110 #
b11100100001110 <
1$
#1091000
b11100010001111 6
b1101000011100101 5
b11111111111111111111111111000000 :
b100111111010100001100000 7
b11100010001111 9
b11101110001 &
b11101110001 /
0+
#1100000
0$
#1110000
1$
#1111000
1+
#1120000
0$
#1130000
b1101000100100101 5
b0 :
b11100010001111 ?
b11100010001111 #
b11100010001111 <
1$
#1131000
b11100000010000 6
b1101000001100110 5
b11111111111111111111111111000000 :
b100111111001100010000000 7
b11100000010000 9
b11111110000 &
b11111110000 /
0+
#1140000
0$
#1150000
1$
#1151000
1+
#1160000
0$
#1170000
b1101000010100110 5
b0 :
b11100000010000 ?
b11100000010000 #
b11100000010000 <
1$
#1171000
b11011110010001 6
b1100111111100111 5
b11111111111111111111111111000000 :
b100111111000100010100000 7
b11011110010001 9
b100001101111 &
b100001101111 /
0+
#1180000
0$
#1190000
1$
#1191000
1+
#1200000
0$
#1210000
b1101000000100111 5
b0 :
b11011110010001 ?
b11011110010001 #
b11011110010001 <
1$
#1211000
b11011100010010 6
b1100111101101000 5
b11111111111111111111111111000000 :
b100111110111100011000000 7
b11011100010010 9
b100011101110 &
b100011101110 /
0+
#1220000
0$
#1230000
1$
#1231000
1+
#1240000
0$
#1250000
b1100111110101000 5
b0 :
b11011100010010 ?
b11011100010010 #
b11011100010010 <
1$
#1251000
b11011010010011 6
b1100111011101001 5
b11111111111111111111111111000000 :
b100111110110100011100000 7
b11011010010011 9
b100101101101 &
b100101101101 /
0+
#1260000
0$
#1270000
1$
#1271000
1+
#1280000
0$
#1290000
b1100111100101001 5
b0 :
b11011010010011 ?
b11011010010011 #
b11011010010011 <
1$
#1291000
b11011000010100 6
b1100111001101010 5
b11111111111111111111111111000000 :
b100111110101100100000000 7
b11011000010100 9
b100111101100 &
b100111101100 /
0+
#1300000
0$
#1310000
1$
#1311000
1+
#1320000
0$
#1330000
b1100111010101010 5
b0 :
b11011000010100 ?
b11011000010100 #
b11011000010100 <
1$
#1331000
b11010110010101 6
b1100110111101011 5
b11111111111111111111111111000000 :
b100111110100100100100000 7
b11010110010101 9
b101001101011 &
b101001101011 /
0+
#1340000
0$
#1350000
1$
#1351000
1+
#1360000
0$
#1370000
b1100111000101011 5
b0 :
b11010110010101 ?
b11010110010101 #
b11010110010101 <
1$
#1371000
b11010100010110 6
b1100110101101100 5
b11111111111111111111111111000000 :
b100111110011100101000000 7
b11010100010110 9
b101011101010 &
b101011101010 /
0+
#1380000
0$
#1390000
1$
#1391000
1+
#1400000
0$
#1410000
b1100110110101100 5
b0 :
b11010100010110 ?
b11010100010110 #
b11010100010110 <
1$
#1411000
b11010010010111 6
b1100110011101101 5
b11111111111111111111111111000000 :
b100111110010100101100000 7
b11010010010111 9
b101101101001 &
b101101101001 /
0+
#1420000
0$
#1430000
1$
#1431000
1+
#1440000
0$
#1450000
b1100110100101101 5
b0 :
b11010010010111 ?
b11010010010111 #
b11010010010111 <
1$
#1451000
b11010000011000 6
b1100110001101110 5
b11111111111111111111111111000000 :
b100111110001100110000000 7
b11010000011000 9
b101111101000 &
b101111101000 /
0+
#1460000
0$
#1470000
1$
#1471000
1+
#1480000
0$
#1490000
b1100110010101110 5
b0 :
b11010000011000 ?
b11010000011000 #
b11010000011000 <
1$
#1491000
b11001110011001 6
b1100101111101111 5
b11111111111111111111111111000000 :
b100111110000100110100000 7
b11001110011001 9
b110001100111 &
b110001100111 /
0+
#1500000
0$
#1510000
1$
#1511000
1+
#1520000
0$
#1530000
b1100110000101111 5
b0 :
b11001110011001 ?
b11001110011001 #
b11001110011001 <
1$
#1531000
b11001100011010 6
b1100101101110000 5
b11111111111111111111111111000000 :
b100111101111100111000000 7
b11001100011010 9
b110011100110 &
b110011100110 /
0+
#1540000
0$
#1550000
1$
#1551000
1+
#1560000
0$
#1570000
b1100101110110000 5
b0 :
b11001100011010 ?
b11001100011010 #
b11001100011010 <
1$
#1571000
b11001010011011 6
b1100101011110001 5
b11111111111111111111111111000000 :
b100111101110100111100000 7
b11001010011011 9
b110101100101 &
b110101100101 /
0+
#1580000
0$
#1590000
1$
#1591000
1+
#1600000
0$
#1610000
b1100101100110001 5
b0 :
b11001010011011 ?
b11001010011011 #
b11001010011011 <
1$
#1611000
b11001000011100 6
b1100101001110010 5
b11111111111111111111111111000000 :
b100111101101101000000000 7
b11001000011100 9
b110111100100 &
b110111100100 /
0+
#1620000
0$
#1630000
1$
#1631000
1+
#1640000
0$
#1650000
b1100101010110010 5
b0 :
b11001000011100 ?
b11001000011100 #
b11001000011100 <
1$
#1651000
b11000110011101 6
b1100100111110011 5
b11111111111111111111111111000000 :
b100111101100101000100000 7
b11000110011101 9
b111001100011 &
b111001100011 /
0+
#1660000
0$
#1670000
1$
#1671000
1+
#1680000
0$
#1690000
b1100101000110011 5
b0 :
b11000110011101 ?
b11000110011101 #
b11000110011101 <
1$
#1691000
b11000100011110 6
b1100100101110100 5
b11111111111111111111111111000000 :
b111111111111111 @
0%
b100111101011101001000000 7
b11000100011110 9
b111011100010 &
b111011100010 /
0+
#1700000
0$
#1710000
1$
#1711000
1+
#1720000
0$
#1730000
1$
#1731000
0+
#1740000
0$
#1750000
1$
#1751000
1+
#1760000
0$
#1770000
1$
#1771000
1*
b10 .
0+
#1780000
0$
#1790000
b1100010001111 :
b100100110101101 5
b0 8
b0 #
b0 <
b0 !
b0 >
b0 ?
b1100010001111000000 7
b0 "
b0 0
b0 =
1$
#1791000
0*
#1800000
0$
#1810000
1$
#1811000
b11 .
